panns_hear/__init__.py
panns_hear/models.py
panns_hear/panns.py
panns_hear/pytorch_utils.py
panns_hear-0.2.1.dist-info/LICENSE
panns_hear-0.2.1.dist-info/METADATA
panns_hear-0.2.1.dist-info/WHEEL
panns_hear-0.2.1.dist-info/top_level.txt
panns_hear-0.2.1.dist-info/RECORD
